epubcfi/__init__.py
epubcfi/assertion.py
epubcfi/cfi.py
epubcfi/error.py
epubcfi/parser.py
epubcfi/path.py
epubcfi/token.py
epubcfi/tokenizer.py
epubcfi/__pycache__/__init__.cpython-312.pyc
epubcfi/__pycache__/assertion.cpython-312.pyc
epubcfi/__pycache__/cfi.cpython-312.pyc
epubcfi/__pycache__/error.cpython-312.pyc
epubcfi/__pycache__/parser.cpython-312.pyc
epubcfi/__pycache__/path.cpython-312.pyc
epubcfi/__pycache__/token.cpython-312.pyc
epubcfi/__pycache__/tokenizer.cpython-312.pyc
epubcfi/cfi/__init__.py
epubcfi/cfi/assertion.py
epubcfi/cfi/error.py
epubcfi/cfi/handler.py
epubcfi/cfi/parser.py
epubcfi/cfi/path.py
epubcfi/cfi/token.py
epubcfi/cfi/tokenizer.py
epubcfi/epub/__init__.py
epubcfi/epub/handler.py
epubcfi/epub/ncx_finder.py
epubcfi/epub/picker.py
epubcfi/epub/stepper.py
epubcfi/epub/unzip.py
epubcfi/epub/utils.py
epubcfi-0.0.6.dist-info/METADATA
epubcfi-0.0.6.dist-info/WHEEL
epubcfi-0.0.6.dist-info/top_level.txt
epubcfi-0.0.6.dist-info/RECORD
