Metadata-Version: 2.2
Name: epubcfi
Version: 0.0.6
Summary: handle Epub CFI
Author: Tao Zeyu
Author-email: i@taozeyu.com
Requires-Dist: lxml<6.0,>=5.3.0
Dynamic: author
Dynamic: author-email
Dynamic: description
Dynamic: description-content-type
Dynamic: requires-dist
Dynamic: summary
